{
	"info": {
		"_postman_id": "97e22172-08ee-4a5d-94d9-ac77b2ef11f3",
		"name": "New Collection",
		"schema": "https://schema.getpostman.com/json/collection/v2.1.0/collection.json",
		"_exporter_id": "33195856"
	},
	"item": [
		{
			"name": "https://api.nasa.gov",
			"request": {
				"method": "GET",
				"header": [
					{
						"key": "api_key",
						"value": "4EdY1Xggk8wNQQWrVeg3PxT3KjL0UWUDQVheQhM8",
						"type": "text"
					}
				],
				"url": {
					"raw": "https://api.nasa.gov",
					"protocol": "https",
					"host": [
						"api",
						"nasa",
						"gov"
					]
				}
			},
			"response": []
		}
	]
}